config_models/__init__.py
config_models/admin.py
config_models/apps.py
config_models/decorators.py
config_models/models.py
config_models/templatetags.py
config_models/urls.py
config_models/utils.py
config_models/views.py
config_models/management/__init__.py
config_models/management/commands/__init__.py
config_models/management/commands/populate_model.py
config_models/templates/config_models/base.html
django_config_models-2.9.0.dist-info/licenses/AUTHORS
django_config_models-2.9.0.dist-info/licenses/LICENSE.txt
django_config_models-2.9.0.dist-info/METADATA
django_config_models-2.9.0.dist-info/WHEEL
django_config_models-2.9.0.dist-info/top_level.txt
django_config_models-2.9.0.dist-info/RECORD
